umidiparser/__init__.py
umidiparser/umidiparser.py
umidiparser-1.2.dist-info/METADATA
umidiparser-1.2.dist-info/WHEEL
umidiparser-1.2.dist-info/licenses/LICENSE
umidiparser-1.2.dist-info/RECORD
