Metadata-Version: 2.1
Name: umidiparser
Version: 1.2
Summary: umidiparser - low footprint MIDI file parser for Micropython, CircuitPython and Python
Project-URL: Homepage, https://github.com/bixb922/umidiparser
Project-URL: Bug Tracker, https://github.com/bixb922/umidiparser/issues
Project-URL: Blog, https://solazyasueto.blogspot.com
Author-email: Hermann von Borries <bixb922@gmail.com>
License: MIT License
License-File: LICENSE
Classifier: Intended Audience :: Developers
Classifier: License :: OSI Approved :: MIT License
Classifier: Operating System :: OS Independent
Classifier: Programming Language :: Python :: 3
Classifier: Programming Language :: Python :: 3.9
Classifier: Programming Language :: Python :: 3.10
Classifier: Programming Language :: Python :: Implementation :: CPython
Classifier: Programming Language :: Python :: Implementation :: MicroPython
Classifier: Topic :: Multimedia :: Sound/Audio :: MIDI
Requires-Python: >=3.9
